update-conan-local/__init__.py
update-conan-local/find_cache.py
update_conan_local/__init__.py
update_conan_local/find_cache.py
update_conan_local/main.py
update_conan_local-0.0.1.post6.dist-info/LICENSE
update_conan_local-0.0.1.post6.dist-info/METADATA
update_conan_local-0.0.1.post6.dist-info/WHEEL
update_conan_local-0.0.1.post6.dist-info/top_level.txt
update_conan_local-0.0.1.post6.dist-info/RECORD
